greenwavereality/__init__.py
greenwavereality/greenwavereality.py
greenwavereality-0.5.1.dist-info/DESCRIPTION.rst
greenwavereality-0.5.1.dist-info/METADATA
greenwavereality-0.5.1.dist-info/RECORD
greenwavereality-0.5.1.dist-info/WHEEL
greenwavereality-0.5.1.dist-info/metadata.json
greenwavereality-0.5.1.dist-info/top_level.txt
