Metadata-Version: 2.0
Name: greenwavereality
Version: 0.5.1
Summary: Control of Greenwave Reality Lights
Home-page: https://github.com/dfiel/greenwavereality
Author: David Fiel
Author-email: github@dfiel.com
License: MIT
Platform: UNKNOWN
Requires-Dist: requests
Requires-Dist: xmltodict
Requires-Dist: urllib3
